djmicroservice/__init__.py
djmicroservice/admin.py
djmicroservice/apps.py
djmicroservice/client.py
djmicroservice/mixins.py
djmicroservice/models.py
djmicroservice/pagination.py
djmicroservice/permissions.py
djmicroservice/settings.py
djmicroservice/signals.py
djmicroservice/tests.py
djmicroservice/validators.py
djmicroservice/views.py
djmicroservice/discovers/__init__.py
djmicroservice/discovers/backends.py
djmicroservice/discovers/discover.py
djmicroservice/management/__init__.py
djmicroservice/management/commands/__init__.py
djmicroservice/management/commands/djmsmanage.py
djmicroservice/management/commands/djmsservice.py
djmicroservice/migrations/__init__.py
djmicroservice/mq/__init__.py
djmicroservice/mq/client.py
djmicroservice/mq/handlers.py
djmicroservice/mq/backends/__init__.py
djmicroservice/mq/backends/activemq.py
djmicroservice/mq/backends/base.py
djmicroservice/serializers/__init__.py
djmicroservice/serializers/fields.py
djmicroservice/service/__init__.py
djmicroservice/service/base.py
djmicroservice/service/manager.py
djmicroservice/service/monitor.py
djmicroservice/utils/__init__.py
djmicroservice/utils/apollosettings.py
djmicroservice/utils/objectid.py
djmicroservice-1.0.7.dist-info/METADATA
djmicroservice-1.0.7.dist-info/WHEEL
djmicroservice-1.0.7.dist-info/top_level.txt
djmicroservice-1.0.7.dist-info/RECORD
