Metadata-Version: 2.1
Name: djmicroservice
Version: 1.0.7
Summary: django micro service app.
Home-page: https://github.com/tangdyy/djmicroservice
Author: Tang dayong
Author-email: 674822668@qq.com
License: UNKNOWN
Platform: UNKNOWN
Classifier: Programming Language :: Python :: 3
Classifier: License :: OSI Approved :: MIT License
Classifier: Operating System :: OS Independent
Requires: django
Requires: djangorestframework
Requires-Python: >=3.6
